{
	"utilities": {
		"telosServer": {
			"source": "telos-server/telosServer.js",
			"properties": {
				"tags": ["telos-module"]
			}
		},
		"telosRouter": {
			"source": "telos-server/telosRouter.js",
			"properties": {
				"tags": ["telos-module"]
			}
		},
		"telosWrap": {
			"source": "telos-server/telosWrap.js",
			"properties": {
				"tags": ["telos-module"]
			}
		},
		"telosMiddleware": {
			"source": "telos-server/telosMiddleware.js",
			"properties": {
				"tags": ["telos-server-middleware"]
			}
		}
	}
}